common/__init__.py
common/ai.py
common/analysis.py
common/control.py
common/data_load.py
common/decorator.py
common/dr.py
common/first.py
common/model_training.py
common/monitoring.py
common/sql_make.py
aihems-0.0.dist-info/METADATA
aihems-0.0.dist-info/WHEEL
aihems-0.0.dist-info/top_level.txt
aihems-0.0.dist-info/RECORD
